{
  "feedback_entries": [
    {
      "timestamp": "2025-08-03T02:49:21.595402",
      "chapter_number": 1,
      "prompt_hash": "998fa1af57e8a3cd",
      "quality_score": 0.613,
      "language": "de",
      "user_rating": 4,
      "user_comment": "Gute Grundstruktur, aber könnte mehr emotionale Tiefe haben",
      "metadata": {}
    },
    {
      "timestamp": "2025-08-03T02:49:21.596033",
      "chapter_number": 1,
      "prompt_hash": "998fa1af57e8a3cd",
      "quality_score": 0.613,
      "language": "en",
      "user_rating": 3,
      "user_comment": "Solid foundation, needs more engaging dialogue",
      "metadata": {}
    },
    {
      "timestamp": "2025-08-03T02:49:21.596451",
      "chapter_number": 1,
      "prompt_hash": "2fc47a0ccbcd3210",
      "quality_score": 0.613,
      "language": "de",
      "user_rating": 4,
      "user_comment": "Sehr gute emotionale Tiefe und bildhafte Sprache",
      "metadata": {}
    },
    {
      "timestamp": "2025-08-03T02:49:21.596837",
      "chapter_number": 1,
      "prompt_hash": "2fc47a0ccbcd3210",
      "quality_score": 0.613,
      "language": "en",
      "user_rating": 3,
      "user_comment": "Much better emotional engagement and dialogue",
      "metadata": {}
    },
    {
      "timestamp": "2025-08-03T02:56:58.627650",
      "chapter_number": 1,
      "prompt_hash": "d5ffd10afbe83c0a",
      "quality_score": 0.509,
      "language": "de",
      "user_rating": 3,
      "user_comment": "Durchschnittliche Qualität, Verbesserungspotential vorhanden",
      "metadata": {}
    },
    {
      "timestamp": "2025-08-03T15:01:09.890090",
      "chapter_number": 1,
      "prompt_hash": "4856557e12402094",
      "quality_score": 0.0,
      "language": "de",
      "user_rating": 2,
      "user_comment": "Qualität verbesserungsbedürftig für adventure",
      "metadata": {
        "age_group": "early_reader",
        "genre": "adventure",
        "emotion": "courage",
        "evaluation_scores": {
          "readability": 0.0,
          "age_appropriateness": 0.0,
          "genre_compliance": 0.0,
          "emotional_depth": 0.0,
          "engagement": 0.0
        }
      }
    },
    {
      "timestamp": "2025-08-03T15:03:16.245293",
      "chapter_number": 1,
      "prompt_hash": "9f5efba5786efd23",
      "quality_score": 0.0,
      "language": "de",
      "user_rating": 2,
      "user_comment": "Qualität verbesserungsbedürftig für fantasy",
      "metadata": {
        "age_group": "middle_grade",
        "genre": "fantasy",
        "emotion": "wonder",
        "evaluation_scores": {
          "readability": 0.0,
          "age_appropriateness": 0.0,
          "genre_compliance": 0.0,
          "emotional_depth": 0.0,
          "engagement": 0.0
        }
      }
    },
    {
      "timestamp": "2025-08-03T15:17:40.552343",
      "chapter_number": 1,
      "prompt_hash": "4856557e12402094",
      "quality_score": 0.0,
      "language": "de",
      "user_rating": 2,
      "user_comment": "Qualität verbesserungsbedürftig für adventure",
      "metadata": {
        "age_group": "early_reader",
        "genre": "adventure",
        "emotion": "courage",
        "evaluation_scores": {
          "readability": 0.0,
          "age_appropriateness": 0.0,
          "genre_compliance": 0.0,
          "emotional_depth": 0.0,
          "engagement": 0.0
        }
      }
    },
    {
      "timestamp": "2025-08-03T15:19:52.955145",
      "chapter_number": 1,
      "prompt_hash": "9f5efba5786efd23",
      "quality_score": 0.0,
      "language": "de",
      "user_rating": 2,
      "user_comment": "Qualität verbesserungsbedürftig für fantasy",
      "metadata": {
        "age_group": "middle_grade",
        "genre": "fantasy",
        "emotion": "wonder",
        "evaluation_scores": {
          "readability": 0.0,
          "age_appropriateness": 0.0,
          "genre_compliance": 0.0,
          "emotional_depth": 0.0,
          "engagement": 0.0
        }
      }
    },
    {
      "timestamp": "2025-08-03T15:22:03.941565",
      "chapter_number": 1,
      "prompt_hash": "e5f92a8437143b1b",
      "quality_score": 0.0,
      "language": "de",
      "user_rating": 2,
      "user_comment": "Qualität verbesserungsbedürftig für self_discovery",
      "metadata": {
        "age_group": "young_adult",
        "genre": "self_discovery",
        "emotion": "growth",
        "evaluation_scores": {
          "readability": 0.0,
          "age_appropriateness": 0.0,
          "genre_compliance": 0.0,
          "emotional_depth": 0.0,
          "engagement": 0.0
        }
      }
    }
  ],
  "statistics": {
    "overall": {
      "total_entries": 10,
      "avg_rating": 2.7,
      "avg_quality_score": 0.2961,
      "rating_std": 0.8232726023485646,
      "quality_std": 0.31365318780816215
    },
    "by_prompt_hash": {
      "998fa1af57e8a3cd": {
        "count": 2,
        "ratings": [
          4,
          3
        ],
        "quality_scores": [
          0.613,
          0.613
        ],
        "avg_rating": 3.5,
        "avg_quality_score": 0.613,
        "rating_std": 0.7071067811865476,
        "quality_std": 0.0
      },
      "2fc47a0ccbcd3210": {
        "count": 2,
        "ratings": [
          4,
          3
        ],
        "quality_scores": [
          0.613,
          0.613
        ],
        "avg_rating": 3.5,
        "avg_quality_score": 0.613,
        "rating_std": 0.7071067811865476,
        "quality_std": 0.0
      },
      "d5ffd10afbe83c0a": {
        "count": 1,
        "ratings": [
          3
        ],
        "quality_scores": [
          0.509
        ],
        "avg_rating": 3,
        "avg_quality_score": 0.509,
        "rating_std": 0,
        "quality_std": 0
      },
      "4856557e12402094": {
        "count": 2,
        "ratings": [
          2,
          2
        ],
        "quality_scores": [
          0.0,
          0.0
        ],
        "avg_rating": 2,
        "avg_quality_score": 0.0,
        "rating_std": 0.0,
        "quality_std": 0.0
      },
      "9f5efba5786efd23": {
        "count": 2,
        "ratings": [
          2,
          2
        ],
        "quality_scores": [
          0.0,
          0.0
        ],
        "avg_rating": 2,
        "avg_quality_score": 0.0,
        "rating_std": 0.0,
        "quality_std": 0.0
      },
      "e5f92a8437143b1b": {
        "count": 1,
        "ratings": [
          2
        ],
        "quality_scores": [
          0.0
        ],
        "avg_rating": 2,
        "avg_quality_score": 0.0,
        "rating_std": 0,
        "quality_std": 0
      }
    },
    "last_updated": "2025-08-03T15:22:03.942173"
  },
  "metadata": {
    "created": "2025-08-03T02:48:15.431168",
    "total_entries": 10
  }
}